pve_cloud_test/_version.py
pve_cloud_test/cloud_fixtures.py
pve_cloud_test/k8s_fixtures.py
pve_cloud_test/options.py
pve_cloud_test/tdd_watchdog.py
pve_cloud_test/terraform.py
pve_cloud_test/test_env_schema.yaml
pytest_pve_cloud-0.8.3.dist-info/licenses/LICENSE.md
pytest_pve_cloud-0.8.3.dist-info/METADATA
pytest_pve_cloud-0.8.3.dist-info/WHEEL
pytest_pve_cloud-0.8.3.dist-info/entry_points.txt
pytest_pve_cloud-0.8.3.dist-info/top_level.txt
pytest_pve_cloud-0.8.3.dist-info/RECORD
