Metadata-Version: 2.4
Name: pytest-pve-cloud
Version: 0.8.3
Author-email: Tobias Huebner <tobias.huebner@vmzberlin.com>
License-Expression: GPL-3.0-or-later
License-File: LICENSE.md
Requires-Dist: py-pve-cloud<0.16.0,>=0.15.5
Requires-Dist: kubernetes==34.1.0
Requires-Dist: pytest==8.4.2
Requires-Dist: ansible-runner==2.4.2
Requires-Dist: redis==7.1.0
Requires-Dist: watchdog==6.0.0
Requires-Dist: twine==6.2.0
Requires-Dist: netifaces==0.11.0
Requires-Dist: rpyc==6.0.2
Requires-Dist: moto[route53]==5.1.19
Requires-Dist: semver==3.0.4
Requires-Dist: pytest-asyncio==1.3.0
Dynamic: license-file
